{
  "project_info": {
    "project_number": "393321453673",
    "project_id": "racroad",
    "storage_bucket": "racroad.appspot.com"
  },
  "client": [
    {
      "client_info": {
        "mobilesdk_app_id": "1:393321453673:android:c7a2d2821684a9b6016af8",
        "android_client_info": {
          "package_name": "com.medbuddy.racroad"
        }
      },
      "oauth_client": [
        {
          "client_id": "393321453673-dg5cfmcmetuthirghh8mc1k568qp4163.apps.googleusercontent.com",
          "client_type": 1,
          "android_info": {
            "package_name": "com.medbuddy.racroad",
            "certificate_hash": "4164505c7fcaa5184418c4cc2372b74519478845"
          }
        },
        {
          "client_id": "393321453673-i5lkqtum0llk0okvnvig51ccho0r4se3.apps.googleusercontent.com",
          "client_type": 1,
          "android_info": {
            "package_name": "com.medbuddy.racroad",
            "certificate_hash": "440e83575cc2b47307cbe6133a2afbd4dc35fb1c"
          }
        },
        {
          "client_id": "393321453673-mo4n2rhq7k9jhnmbbc5poui68k7v80d5.apps.googleusercontent.com",
          "client_type": 1,
          "android_info": {
            "package_name": "com.medbuddy.racroad",
            "certificate_hash": "a303884980ed5702a05d8a1456d43cd8ecc774bc"
          }
        },
        {
          "client_id": "393321453673-keicn92mu4jauh32g3nmcfh7prrv2ge7.apps.googleusercontent.com",
          "client_type": 3
        }
      ],
      "api_key": [
        {
          "current_key": "AIzaSyAC4kZwId4ZylE6AHIUiUq9Xuhy4xmDJlo"
        }
      ],
      "services": {
        "appinvite_service": {
          "other_platform_oauth_client": [
            {
              "client_id": "393321453673-keicn92mu4jauh32g3nmcfh7prrv2ge7.apps.googleusercontent.com",
              "client_type": 3
            },
            {
              "client_id": "393321453673-b4vosdnr9a775hs8s7lqjum9ef91ej6v.apps.googleusercontent.com",
              "client_type": 2,
              "ios_info": {
                "bundle_id": "com.racroad.RacRoadApp"
              }
            }
          ]
        }
      }
    }
  ],
  "configuration_version": "1"
}